admin_interface/__init__.py
admin_interface/admin.py
admin_interface/apps.py
admin_interface/cache.py
admin_interface/metadata.py
admin_interface/models.py
admin_interface/settings.py
admin_interface/fixtures/admin_interface_theme_bootstrap.json
admin_interface/fixtures/admin_interface_theme_django.json
admin_interface/fixtures/admin_interface_theme_foundation.json
admin_interface/fixtures/admin_interface_theme_uswds.json
admin_interface/fixtures/initial_data.json
admin_interface/locale/de/LC_MESSAGES/django.mo
admin_interface/locale/de/LC_MESSAGES/django.po
admin_interface/locale/es/LC_MESSAGES/django.mo
admin_interface/locale/es/LC_MESSAGES/django.po
admin_interface/locale/fa/LC_MESSAGES/django.mo
admin_interface/locale/fa/LC_MESSAGES/django.po
admin_interface/locale/fr/LC_MESSAGES/django.mo
admin_interface/locale/fr/LC_MESSAGES/django.po
admin_interface/locale/it/LC_MESSAGES/django.mo
admin_interface/locale/it/LC_MESSAGES/django.po
admin_interface/locale/pl/LC_MESSAGES/django.mo
admin_interface/locale/pl/LC_MESSAGES/django.po
admin_interface/locale/pt_BR/LC_MESSAGES/django.mo
admin_interface/locale/pt_BR/LC_MESSAGES/django.po
admin_interface/locale/ru/LC_MESSAGES/django.mo
admin_interface/locale/ru/LC_MESSAGES/django.po
admin_interface/locale/tr/LC_MESSAGES/django.mo
admin_interface/locale/tr/LC_MESSAGES/django.po
admin_interface/migrations/0001_initial.py
admin_interface/migrations/0002_add_related_modal.py
admin_interface/migrations/0003_add_logo_color.py
admin_interface/migrations/0004_rename_title_color.py
admin_interface/migrations/0005_add_recent_actions_visible.py
admin_interface/migrations/0006_bytes_to_str.py
admin_interface/migrations/0007_add_favicon.py
admin_interface/migrations/0008_change_related_modal_background_opacity_type.py
admin_interface/migrations/0009_add_enviroment.py
admin_interface/migrations/0010_add_localization.py
admin_interface/migrations/0011_add_environment_options.py
admin_interface/migrations/0012_update_verbose_names.py
django_admin_interface-0.29.2.dist-info/LICENSE.txt
django_admin_interface-0.29.2.dist-info/METADATA
django_admin_interface-0.29.2.dist-info/WHEEL
django_admin_interface-0.29.2.dist-info/top_level.txt
django_admin_interface-0.29.2.dist-info/RECORD
