Metadata-Version: 2.1
Name: django-admin-interface
Version: 0.29.2
Summary: django's default admin interface with superpowers - customizable themes, popup windows replaced by modals and many other features.
Author-email: Fabio Caccamo <fabio.caccamo@gmail.com>
Maintainer-email: Fabio Caccamo <fabio.caccamo@gmail.com>
License: The MIT License (MIT)
Project-URL: Homepage, https://github.com/fabiocaccamo/django-admin-interface
Project-URL: Download, https://github.com/fabiocaccamo/django-admin-interface/releases
Project-URL: Documentation, https://github.com/fabiocaccamo/django-admin-interface#readme
Project-URL: Issues, https://github.com/fabiocaccamo/django-admin-interface/issues
Project-URL: Funding, https://github.com/sponsors/fabiocaccamo/
Project-URL: Twitter, https://twitter.com/fabiocaccamo
Keywords: django,admin,interface,responsive,flat,theme,custom,ui
Classifier: Development Status :: 5 - Production/Stable
Classifier: Environment :: Web Environment
Classifier: Framework :: Django
Classifier: Framework :: Django :: 4.0
Classifier: Framework :: Django :: 4.1
Classifier: Framework :: Django :: 4.2
Classifier: Framework :: Django :: 5.0
Classifier: Framework :: Django :: 5.1
Classifier: Intended Audience :: Developers
Classifier: License :: OSI Approved :: MIT License
Classifier: Natural Language :: English
Classifier: Operating System :: OS Independent
Classifier: Programming Language :: Python :: 3
Classifier: Programming Language :: Python :: 3.10
Classifier: Programming Language :: Python :: 3.11
Classifier: Programming Language :: Python :: 3.12
Classifier: Programming Language :: Python :: 3.13
Classifier: Topic :: Software Development :: Build Tools
License-File: LICENSE.txt
Requires-Dist: django-colorfield<1.0.0,>=0.8.0
Requires-Dist: python-slugify<9.0.0,>=7.0.0
